tendaysweb
