Metadata-Version: 1.2
Name: 10daysweb
Version: 0.1.1
Summary: Async web framework for learning
Home-page: https://github.com/bace1996/10daysWeb
Author: Cykrt Chan
License: MIT
Keywords: web framework async
Platform: UNKNOWN
Classifier: Development Status :: 3 - Alpha
Classifier: Intended Audience :: Developers
Classifier: Environment :: Web Environment
Classifier: License :: OSI Approved :: MIT License
Classifier: Programming Language :: Python :: 3.6
Requires-Python: >=3.6
